[
  {
    "coords": [22.719784060261762, 75.85593361116833],
    "intensity": 0.53,
    "name": "Ward 1",
    "info": { "sector": "Rajwada", "revenue": 10, "totalrevenue": 2 }
  },
  {
    "coords": [22.72149611458743, 75.84826745653889],
    "intensity": 0.53,
    "name": "Ward 2",
    "info": { "sector": "sapna sangita", "revenue": 20, "totalrevenue": 5 }
  },
  {
    "coords": [22.69519936984291, 75.87329350997148],
    "intensity": 0.53,
    "name": "Ward 3",
    "info": { "sector": "mr-10", "revenue": 30, "totalrevenue": 5 }
  },
  {
    "coords": [22.740168980449706, 75.85560745872762],
    "intensity": 0.53,
    "name": "Ward 4",
    "info": { "sector": "Bangana", "revenue": 40, "totalrevenue": 5 }
  },
  {
    "coords": [22.737002590248636, 75.9220020943885],
    "intensity": 0.53,
    "name": "Ward 5",
    "info": { "sector": "Bhawarkua", "revenue": 50, "totalrevenue": 5 }
  }
]
